PyBharat/Cinema.py
PyBharat/Entertainment.py
PyBharat/National.py
PyBharat/NationalSymbol.py
PyBharat/__init__.py
PyBharat/agriculture.py
PyBharat/award.py
PyBharat/ayurveda.py
PyBharat/climate.py
PyBharat/company.py
PyBharat/culture.py
PyBharat/ecommerce.py
PyBharat/emergency_contact.py
PyBharat/exam.py
PyBharat/festival.py
PyBharat/finance.py
PyBharat/geography.py
PyBharat/healthcare.py
PyBharat/historicalplace.py
PyBharat/indian_exports_imports.py
PyBharat/invention.py
PyBharat/law.py
PyBharat/name.py
PyBharat/rare_facts.py
PyBharat/river.py
PyBharat/setup.py
PyBharat/space.py
PyBharat/sport.py
PyBharat/state.py
PyBharat/superstition.py
PyBharat/temple.py
PyBharat/traffic_transport.py
PyBharat/unit.py
pybharat-0.0.2.dist-info/licenses/LICENSE
pybharat-0.0.2.dist-info/METADATA
pybharat-0.0.2.dist-info/WHEEL
pybharat-0.0.2.dist-info/top_level.txt
pybharat-0.0.2.dist-info/RECORD
