Metadata-Version: 2.4
Name: PyBharat
Version: 0.0.2
Summary: PyBharat is a cultural-flavored Python library that blends Indian heritage with powerful programming tools. It offers utilities, data, and functions rooted in India — from national symbols, festivals, and state details to greeting styles, traditional mantras, and more.
Home-page: https://github.com/JaiServanaBhava/PyBharat
Author: Jai Servana Bhava
Author-email: jai005servanbhava@gmail.com
Classifier: Programming Language :: Python :: 3
Classifier: License :: OSI Approved :: MIT License
Classifier: Operating System :: OS Independent
Requires-Python: >=3.6
License-File: LICENSE
Dynamic: author
Dynamic: author-email
Dynamic: classifier
Dynamic: description
Dynamic: description-content-type
Dynamic: home-page
Dynamic: license-file
Dynamic: requires-python
Dynamic: summary
